src/__init__.py
src/app.py
src/beckett/__init__.py
src/beckett/app.py
src/beckett/blueprint.py
src/beckett/renderer/README.md
src/beckett/renderer/__init__.py
src/beckett/renderer/html/__init__.py
src/beckett/renderer/html/renderer.py
src/beckett/renderer/typescript_react/__init__.py
src/beckett/renderer/typescript_react/context_processor.py
src/beckett/renderer/typescript_react/imports.py
src/beckett/renderer/typescript_react/interfaces.py
src/beckett/renderer/typescript_react/renderer.py
src/beckett/types/__init__.py
src/beckett/types/types.py
src/beckett/types/types_manager.py
src/cli.py
src/js/api/index.tsx
src/js/api/query.ts
src/js/api/types.ts
src/js/beckett_page.tsx
src/js/components/csrf.tsx
src/js/components/loading.tsx
src/js/template/people/react_example.tsx
src/js/template/people/react_example.type.ts
src/js/template/people/test_page.tsx
src/js/template/people/test_page.type.ts
src/settings.py
src/static/styles.css
src/template/base.jinja2
src/template/beckett_page.jinja2
src/template/beckett_page.template
src/template/index/base_page.jinja2
src/utils.py
src/views/__init__.py
src/views/index.py
src/views/people.py
react_flask-0.1.0.dist-info/METADATA
react_flask-0.1.0.dist-info/WHEEL
react_flask-0.1.0.dist-info/RECORD
