Metadata-Version: 2.1
Name: react-flask
Version: 0.1.0
Summary: Fully typed Flask and React applications
Author: Paul Hallett
Author-email: paulandrewhallett@gmail.com
Requires-Python: >=3.11.2,<4.0.0
Classifier: Programming Language :: Python :: 3
Requires-Dist: Flask (>=2.2.3,<3.0.0)
Requires-Dist: Jinja2 (>=3.1.2,<4.0.0)
Requires-Dist: black (>=23.3.0,<24.0.0)
Requires-Dist: click (>=8.1.3,<9.0.0)
Requires-Dist: inflection (>=0.5.1,<0.6.0)
Requires-Dist: isort (>=5.12.0,<6.0.0)
Requires-Dist: mkdocs (>=1.4.3,<2.0.0)
Requires-Dist: mkdocs-material (>=9.1.13,<10.0.0)
Requires-Dist: mypy (>=1.1.1,<2.0.0)
Requires-Dist: pydantic (>=2.0.3,<3.0.0)
Requires-Dist: ruff (>=0.0.267,<0.0.268)
Requires-Dist: structlog (>=22.3.0,<23.0.0)
Requires-Dist: typing-extensions (>=4.7.1,<5.0.0)
